scru160/__init__.py
scru160/cli/__init__.py
scru160-0.2.3.dist-info/entry_points.txt
scru160-0.2.3.dist-info/LICENSE
scru160-0.2.3.dist-info/WHEEL
scru160-0.2.3.dist-info/METADATA
scru160-0.2.3.dist-info/RECORD
