Metadata-Version: 2.1
Name: scru160
Version: 0.2.3
Summary: SCRU160: Sortable, Clock and Random number-based Unique identifier
Home-page: https://github.com/scru160/python
License: Apache-2.0
Keywords: identifier,uuid,guid,ulid,ksuid
Author: LiosK
Author-email: contact@mail.liosk.net
Requires-Python: >=3.7.12,<4.0.0
Classifier: License :: OSI Approved :: Apache Software License
Classifier: Operating System :: OS Independent
Classifier: Programming Language :: Python :: 3
Classifier: Programming Language :: Python :: 3.8
Classifier: Programming Language :: Python :: 3.9
